[
    {
        "name": "Alfred Clark",
        "age": 46,
        "country": "AU"
    },
    {
        "name": "Deborah Simon",
        "age": 18,
        "country": "FR"
    },
    {
        "name": "Julie Brown",
        "age": 46,
        "country": "CA"
    },
    {
        "name": "Haley Leon",
        "age": 34,
        "country": "CA"
    },
    {
        "name": "Marisa Yang",
        "age": 44,
        "country": "DE"
    },
    {
        "name": "Tracy Smith",
        "age": 22,
        "country": "BR"
    },
    {
        "name": "Caleb Wright",
        "age": 48,
        "country": "JP"
    },
    {
        "name": "Howard Green",
        "age": 53,
        "country": "UK"
    },
    {
        "name": "Dillon Sanchez",
        "age": 31,
        "country": "AU"
    },
    {
        "name": "Calvin Koch",
        "age": 55,
        "country": "FR"
    },
    {
        "name": "Michelle Flynn",
        "age": 57,
        "country": "JP"
    },
    {
        "name": "Brandy Nelson",
        "age": 37,
        "country": "JP"
    },
    {
        "name": "Tanya Ball",
        "age": 46,
        "country": "CA"
    },
    {
        "name": "Eric Williams",
        "age": 47,
        "country": "UK"
    },
    {
        "name": "Kathleen Shaffer",
        "age": 21,
        "country": "US"
    },
    {
        "name": "Eric Carter",
        "age": 39,
        "country": "BR"
    },
    {
        "name": "Benjamin Dawson",
        "age": 26,
        "country": "BR"
    },
    {
        "name": "Mrs. Megan Hall",
        "age": 33,
        "country": "BR"
    },
    {
        "name": "April Reed",
        "age": 40,
        "country": "AU"
    },
    {
        "name": "Michaela Byrd",
        "age": 48,
        "country": "CA"
    },
    {
        "name": "Rebecca Medina",
        "age": 46,
        "country": "DE"
    },
    {
        "name": "Amber Hernandez",
        "age": 45,
        "country": "AU"
    },
    {
        "name": "Darrell Watts",
        "age": 41,
        "country": "AU"
    },
    {
        "name": "Manuel Williams",
        "age": 58,
        "country": "DE"
    },
    {
        "name": "Vincent Walker",
        "age": 42,
        "country": "CA"
    },
    {
        "name": "Jeffrey Allen",
        "age": 51,
        "country": "BR"
    },
    {
        "name": "Heather Dodson",
        "age": 41,
        "country": "FR"
    },
    {
        "name": "Brittany Santos",
        "age": 22,
        "country": "CA"
    },
    {
        "name": "Trevor Reed",
        "age": 35,
        "country": "BR"
    },
    {
        "name": "Brent Woods",
        "age": 49,
        "country": "JP"
    },
    {
        "name": "Shannon Martinez",
        "age": 24,
        "country": "AU"
    },
    {
        "name": "Emily Glenn",
        "age": 19,
        "country": "CA"
    },
    {
        "name": "Dr. Amber Griffin",
        "age": 46,
        "country": "AU"
    },
    {
        "name": "Brian Johnson",
        "age": 49,
        "country": "CA"
    },
    {
        "name": "Amanda Brooks",
        "age": 52,
        "country": "US"
    },
    {
        "name": "Alexandra Joseph",
        "age": 23,
        "country": "DE"
    },
    {
        "name": "Bailey Delgado",
        "age": 26,
        "country": "UK"
    },
    {
        "name": "Brandon Gates",
        "age": 46,
        "country": "BR"
    },
    {
        "name": "John Santos",
        "age": 23,
        "country": "CA"
    },
    {
        "name": "Andrew Davis",
        "age": 32,
        "country": "CA"
    },
    {
        "name": "John King",
        "age": 45,
        "country": "CA"
    },
    {
        "name": "Jennifer Nguyen",
        "age": 54,
        "country": "US"
    },
    {
        "name": "Dennis Martin",
        "age": 41,
        "country": "UK"
    },
    {
        "name": "Julia Medina",
        "age": 51,
        "country": "DE"
    },
    {
        "name": "Joshua Gomez",
        "age": 22,
        "country": "FR"
    },
    {
        "name": "Kelly Rodriguez",
        "age": 55,
        "country": "DE"
    },
    {
        "name": "Nicholas Greer",
        "age": 38,
        "country": "UK"
    },
    {
        "name": "Kayla Lara",
        "age": 23,
        "country": "DE"
    },
    {
        "name": "Lori Gamble",
        "age": 30,
        "country": "US"
    },
    {
        "name": "Kimberly Brown",
        "age": 19,
        "country": "BR"
    },
    {
        "name": "Travis Duffy",
        "age": 36,
        "country": "US"
    },
    {
        "name": "Michael Brown",
        "age": 57,
        "country": "FR"
    },
    {
        "name": "Carmen Walsh",
        "age": 53,
        "country": "CA"
    },
    {
        "name": "Cynthia Lopez",
        "age": 24,
        "country": "BR"
    },
    {
        "name": "Jessica Bell",
        "age": 47,
        "country": "US"
    },
    {
        "name": "Michael Villa",
        "age": 49,
        "country": "UK"
    },
    {
        "name": "Deborah Yu",
        "age": 28,
        "country": "CA"
    },
    {
        "name": "Denise Duncan",
        "age": 38,
        "country": "FR"
    },
    {
        "name": "Thomas Martin",
        "age": 19,
        "country": "BR"
    },
    {
        "name": "Jennifer Sparks",
        "age": 50,
        "country": "JP"
    },
    {
        "name": "Diane Dominguez",
        "age": 27,
        "country": "FR"
    },
    {
        "name": "Amanda Weaver",
        "age": 33,
        "country": "DE"
    },
    {
        "name": "Eric Lane",
        "age": 52,
        "country": "AU"
    },
    {
        "name": "William Rodriguez",
        "age": 50,
        "country": "FR"
    },
    {
        "name": "Grace Wallace",
        "age": 30,
        "country": "UK"
    },
    {
        "name": "Nicole Rich",
        "age": 31,
        "country": "AU"
    },
    {
        "name": "Paul Ortiz",
        "age": 45,
        "country": "US"
    },
    {
        "name": "Francisco Greene",
        "age": 33,
        "country": "DE"
    },
    {
        "name": "Brenda Lowe",
        "age": 35,
        "country": "UK"
    },
    {
        "name": "Kevin Roy",
        "age": 43,
        "country": "AU"
    },
    {
        "name": "Cindy Huerta",
        "age": 45,
        "country": "DE"
    },
    {
        "name": "Amanda Hall",
        "age": 27,
        "country": "US"
    },
    {
        "name": "Gary Vargas",
        "age": 26,
        "country": "DE"
    },
    {
        "name": "Jeffrey Bishop",
        "age": 45,
        "country": "US"
    },
    {
        "name": "Samuel Turner",
        "age": 20,
        "country": "BR"
    },
    {
        "name": "Bruce Perry",
        "age": 38,
        "country": "JP"
    },
    {
        "name": "Jack Fischer",
        "age": 36,
        "country": "JP"
    },
    {
        "name": "Jesse Vasquez",
        "age": 38,
        "country": "US"
    },
    {
        "name": "Melissa Miller",
        "age": 45,
        "country": "BR"
    },
    {
        "name": "Michael King MD",
        "age": 23,
        "country": "JP"
    },
    {
        "name": "Jacqueline Klein",
        "age": 25,
        "country": "UK"
    },
    {
        "name": "Jacob Powell",
        "age": 24,
        "country": "BR"
    },
    {
        "name": "Kendra Moore",
        "age": 53,
        "country": "FR"
    },
    {
        "name": "Amber Jones",
        "age": 45,
        "country": "DE"
    },
    {
        "name": "Daniel Casey",
        "age": 44,
        "country": "AU"
    },
    {
        "name": "William Carr",
        "age": 60,
        "country": "JP"
    },
    {
        "name": "Kenneth Gibbs",
        "age": 52,
        "country": "UK"
    },
    {
        "name": "Willie Bryant",
        "age": 24,
        "country": "DE"
    },
    {
        "name": "Timothy Clark",
        "age": 37,
        "country": "AU"
    },
    {
        "name": "Glenn Ruiz",
        "age": 32,
        "country": "FR"
    },
    {
        "name": "Renee Oconnor",
        "age": 56,
        "country": "AU"
    },
    {
        "name": "Gabriel Hunt",
        "age": 26,
        "country": "US"
    },
    {
        "name": "Amber Smith",
        "age": 33,
        "country": "BR"
    },
    {
        "name": "Jeffrey Perez",
        "age": 45,
        "country": "US"
    },
    {
        "name": "Richard Butler",
        "age": 38,
        "country": "UK"
    },
    {
        "name": "Elizabeth Golden MD",
        "age": 60,
        "country": "CA"
    },
    {
        "name": "Lisa Black",
        "age": 58,
        "country": "BR"
    },
    {
        "name": "Linda Garcia",
        "age": 28,
        "country": "JP"
    },
    {
        "name": "Laura Thompson",
        "age": 55,
        "country": "BR"
    },
    {
        "name": "Thomas Moore",
        "age": 36,
        "country": "JP"
    },
    {
        "name": "Curtis Glass",
        "age": 53,
        "country": "US"
    },
    {
        "name": "Laura Bell",
        "age": 18,
        "country": "JP"
    },
    {
        "name": "Morgan Berry",
        "age": 37,
        "country": "BR"
    },
    {
        "name": "Christine Michael",
        "age": 48,
        "country": "UK"
    },
    {
        "name": "Lisa Ross",
        "age": 59,
        "country": "BR"
    },
    {
        "name": "Zachary Payne",
        "age": 51,
        "country": "DE"
    },
    {
        "name": "William Chung",
        "age": 58,
        "country": "UK"
    },
    {
        "name": "Kyle Moore",
        "age": 28,
        "country": "DE"
    },
    {
        "name": "Emily Thompson",
        "age": 26,
        "country": "UK"
    },
    {
        "name": "Antonio Sanchez",
        "age": 21,
        "country": "DE"
    },
    {
        "name": "Danielle Hood",
        "age": 58,
        "country": "JP"
    },
    {
        "name": "Denise Gutierrez",
        "age": 35,
        "country": "JP"
    },
    {
        "name": "Anthony Compton",
        "age": 59,
        "country": "UK"
    },
    {
        "name": "Linda Mills",
        "age": 32,
        "country": "CA"
    },
    {
        "name": "Michael George",
        "age": 53,
        "country": "AU"
    },
    {
        "name": "Terry Herrera",
        "age": 51,
        "country": "AU"
    },
    {
        "name": "Emily Gilbert",
        "age": 35,
        "country": "AU"
    },
    {
        "name": "Mrs. Elizabeth Morgan",
        "age": 54,
        "country": "DE"
    },
    {
        "name": "Donald Ward",
        "age": 31,
        "country": "BR"
    },
    {
        "name": "Matthew Newton",
        "age": 46,
        "country": "FR"
    },
    {
        "name": "Dr. Theresa Rose",
        "age": 31,
        "country": "AU"
    },
    {
        "name": "Daniel Holden",
        "age": 59,
        "country": "JP"
    },
    {
        "name": "Kimberly Murphy",
        "age": 27,
        "country": "DE"
    },
    {
        "name": "Pamela Ross",
        "age": 21,
        "country": "FR"
    },
    {
        "name": "Tyler Mcdonald",
        "age": 54,
        "country": "BR"
    },
    {
        "name": "Cameron Martin",
        "age": 23,
        "country": "UK"
    },
    {
        "name": "Sonya Ochoa",
        "age": 34,
        "country": "BR"
    },
    {
        "name": "Gabriella Stanton",
        "age": 49,
        "country": "DE"
    },
    {
        "name": "Jordan Turner",
        "age": 53,
        "country": "US"
    },
    {
        "name": "Jessica Lopez",
        "age": 30,
        "country": "JP"
    },
    {
        "name": "Pamela Gregory",
        "age": 35,
        "country": "UK"
    },
    {
        "name": "Kathryn Patton",
        "age": 39,
        "country": "DE"
    },
    {
        "name": "Misty Rivera",
        "age": 50,
        "country": "JP"
    },
    {
        "name": "Timothy Wood",
        "age": 20,
        "country": "FR"
    },
    {
        "name": "Nicole Jones",
        "age": 44,
        "country": "JP"
    },
    {
        "name": "Shannon Kline",
        "age": 18,
        "country": "CA"
    },
    {
        "name": "Luis Nelson",
        "age": 56,
        "country": "BR"
    },
    {
        "name": "Teresa Hernandez",
        "age": 42,
        "country": "US"
    },
    {
        "name": "Fernando Davis",
        "age": 39,
        "country": "CA"
    },
    {
        "name": "Michelle Summers",
        "age": 18,
        "country": "US"
    },
    {
        "name": "Kathryn Brown",
        "age": 53,
        "country": "AU"
    },
    {
        "name": "Carrie Cox",
        "age": 19,
        "country": "US"
    },
    {
        "name": "Tommy Rogers",
        "age": 57,
        "country": "FR"
    },
    {
        "name": "William Hopkins",
        "age": 28,
        "country": "US"
    },
    {
        "name": "Laura Stone",
        "age": 35,
        "country": "UK"
    },
    {
        "name": "Steven Hudson",
        "age": 46,
        "country": "US"
    },
    {
        "name": "Patrick Williams",
        "age": 24,
        "country": "FR"
    },
    {
        "name": "Frederick Robinson",
        "age": 27,
        "country": "CA"
    },
    {
        "name": "Lee Rivera",
        "age": 47,
        "country": "AU"
    },
    {
        "name": "Jeremy Allen",
        "age": 48,
        "country": "CA"
    },
    {
        "name": "James Schmitt",
        "age": 53,
        "country": "JP"
    },
    {
        "name": "Laura Cooper",
        "age": 57,
        "country": "BR"
    },
    {
        "name": "Brittany Williams",
        "age": 53,
        "country": "DE"
    },
    {
        "name": "Kerry Chapman",
        "age": 52,
        "country": "UK"
    },
    {
        "name": "Erin Downs",
        "age": 18,
        "country": "DE"
    },
    {
        "name": "Glenn Murphy",
        "age": 37,
        "country": "UK"
    },
    {
        "name": "Brett Hooper",
        "age": 28,
        "country": "JP"
    },
    {
        "name": "Eric West",
        "age": 53,
        "country": "AU"
    },
    {
        "name": "Stephanie Frederick",
        "age": 46,
        "country": "BR"
    },
    {
        "name": "Cassandra Beard",
        "age": 35,
        "country": "CA"
    },
    {
        "name": "Joshua Hall",
        "age": 59,
        "country": "DE"
    },
    {
        "name": "John Jordan",
        "age": 39,
        "country": "BR"
    },
    {
        "name": "Kathryn Leon",
        "age": 25,
        "country": "DE"
    },
    {
        "name": "Karina Dalton",
        "age": 57,
        "country": "US"
    },
    {
        "name": "Melinda Williams",
        "age": 59,
        "country": "BR"
    },
    {
        "name": "Jimmy Cantrell",
        "age": 32,
        "country": "DE"
    },
    {
        "name": "Russell Fisher",
        "age": 38,
        "country": "JP"
    },
    {
        "name": "Cole Evans",
        "age": 59,
        "country": "DE"
    },
    {
        "name": "William Kelly",
        "age": 51,
        "country": "JP"
    },
    {
        "name": "Christopher Hawkins",
        "age": 40,
        "country": "BR"
    },
    {
        "name": "Jennifer Duncan",
        "age": 47,
        "country": "US"
    },
    {
        "name": "Carlos Mckay",
        "age": 28,
        "country": "JP"
    },
    {
        "name": "Michael Morrow",
        "age": 19,
        "country": "FR"
    },
    {
        "name": "Robert Bell",
        "age": 35,
        "country": "BR"
    },
    {
        "name": "Charles Duncan",
        "age": 40,
        "country": "CA"
    },
    {
        "name": "John Bean",
        "age": 42,
        "country": "JP"
    },
    {
        "name": "Cynthia Cook",
        "age": 59,
        "country": "AU"
    },
    {
        "name": "Nicole Wilson",
        "age": 51,
        "country": "JP"
    },
    {
        "name": "Matthew Hatfield",
        "age": 45,
        "country": "US"
    },
    {
        "name": "Kimberly Lee",
        "age": 50,
        "country": "US"
    },
    {
        "name": "Manuel Garcia",
        "age": 38,
        "country": "US"
    },
    {
        "name": "Dustin Hernandez",
        "age": 21,
        "country": "DE"
    },
    {
        "name": "Gabrielle Harrison",
        "age": 31,
        "country": "CA"
    },
    {
        "name": "Jacob Hart PhD",
        "age": 31,
        "country": "JP"
    },
    {
        "name": "Jacob Park",
        "age": 46,
        "country": "UK"
    },
    {
        "name": "Emily Boyd",
        "age": 46,
        "country": "JP"
    },
    {
        "name": "Lisa Wilson",
        "age": 55,
        "country": "BR"
    },
    {
        "name": "Patrick Webb",
        "age": 57,
        "country": "AU"
    },
    {
        "name": "Angela Pace",
        "age": 47,
        "country": "BR"
    },
    {
        "name": "Erica Cochran",
        "age": 32,
        "country": "US"
    },
    {
        "name": "Melissa Conrad",
        "age": 26,
        "country": "FR"
    },
    {
        "name": "Lisa Carter",
        "age": 51,
        "country": "FR"
    },
    {
        "name": "Lisa Robinson",
        "age": 54,
        "country": "AU"
    },
    {
        "name": "Sherry Taylor",
        "age": 50,
        "country": "CA"
    },
    {
        "name": "Rebecca Barker",
        "age": 50,
        "country": "UK"
    },
    {
        "name": "Kevin Hubbard",
        "age": 45,
        "country": "FR"
    },
    {
        "name": "Todd Butler",
        "age": 56,
        "country": "BR"
    },
    {
        "name": "Jerry Mcdonald",
        "age": 44,
        "country": "JP"
    },
    {
        "name": "Sean Hall",
        "age": 31,
        "country": "DE"
    },
    {
        "name": "Jesse Harris",
        "age": 54,
        "country": "CA"
    },
    {
        "name": "Angela Huerta",
        "age": 44,
        "country": "FR"
    },
    {
        "name": "Christine Moses",
        "age": 44,
        "country": "JP"
    },
    {
        "name": "Jennifer Andrade DDS",
        "age": 19,
        "country": "US"
    },
    {
        "name": "Kendra Hunter",
        "age": 58,
        "country": "CA"
    },
    {
        "name": "Karen Smith",
        "age": 45,
        "country": "DE"
    },
    {
        "name": "Jessica Johnson",
        "age": 18,
        "country": "JP"
    },
    {
        "name": "Travis Palmer",
        "age": 53,
        "country": "CA"
    },
    {
        "name": "Daniel Price",
        "age": 34,
        "country": "CA"
    },
    {
        "name": "Michelle Gray",
        "age": 29,
        "country": "FR"
    },
    {
        "name": "Jason Hubbard",
        "age": 51,
        "country": "DE"
    },
    {
        "name": "Ashley Sullivan",
        "age": 55,
        "country": "CA"
    },
    {
        "name": "Elizabeth Owen",
        "age": 31,
        "country": "BR"
    },
    {
        "name": "Michael Walsh",
        "age": 20,
        "country": "FR"
    },
    {
        "name": "Chloe Anderson",
        "age": 59,
        "country": "FR"
    },
    {
        "name": "Debra Carroll",
        "age": 51,
        "country": "JP"
    },
    {
        "name": "Devin Martin",
        "age": 39,
        "country": "AU"
    },
    {
        "name": "James Neal",
        "age": 31,
        "country": "UK"
    },
    {
        "name": "Gabriel Espinoza",
        "age": 37,
        "country": "AU"
    },
    {
        "name": "Shannon Hurst",
        "age": 39,
        "country": "UK"
    },
    {
        "name": "David Rollins",
        "age": 28,
        "country": "CA"
    },
    {
        "name": "Natalie Hodge",
        "age": 32,
        "country": "DE"
    },
    {
        "name": "Roger Stanley",
        "age": 57,
        "country": "AU"
    },
    {
        "name": "Bethany Jimenez",
        "age": 50,
        "country": "FR"
    },
    {
        "name": "Gary Hernandez",
        "age": 34,
        "country": "DE"
    },
    {
        "name": "Carolyn Kelly",
        "age": 45,
        "country": "AU"
    },
    {
        "name": "Phillip Wade",
        "age": 36,
        "country": "CA"
    },
    {
        "name": "Robert Pugh",
        "age": 41,
        "country": "BR"
    },
    {
        "name": "Benjamin Johnson",
        "age": 45,
        "country": "DE"
    },
    {
        "name": "Dana Gardner",
        "age": 55,
        "country": "JP"
    },
    {
        "name": "Shawn Adkins",
        "age": 47,
        "country": "FR"
    },
    {
        "name": "Jessica Russell",
        "age": 20,
        "country": "JP"
    },
    {
        "name": "Randy Chang",
        "age": 29,
        "country": "US"
    },
    {
        "name": "Michael Cantu",
        "age": 49,
        "country": "AU"
    },
    {
        "name": "Jake Sanders",
        "age": 32,
        "country": "US"
    },
    {
        "name": "Cynthia Bell",
        "age": 33,
        "country": "BR"
    },
    {
        "name": "Mitchell Scott",
        "age": 48,
        "country": "JP"
    },
    {
        "name": "Jennifer Dillon",
        "age": 43,
        "country": "JP"
    },
    {
        "name": "Sean Jones",
        "age": 43,
        "country": "AU"
    },
    {
        "name": "Susan Weber",
        "age": 56,
        "country": "UK"
    },
    {
        "name": "Brian Padilla",
        "age": 31,
        "country": "DE"
    },
    {
        "name": "Charles Stewart",
        "age": 43,
        "country": "DE"
    },
    {
        "name": "Jonathan Ward",
        "age": 51,
        "country": "BR"
    },
    {
        "name": "Audrey Rios",
        "age": 46,
        "country": "CA"
    },
    {
        "name": "David Moreno",
        "age": 30,
        "country": "CA"
    },
    {
        "name": "Adam Whitaker",
        "age": 25,
        "country": "JP"
    },
    {
        "name": "Erika Davidson",
        "age": 32,
        "country": "BR"
    },
    {
        "name": "Ms. Nicole Jones",
        "age": 48,
        "country": "AU"
    },
    {
        "name": "Linda Harding",
        "age": 35,
        "country": "US"
    },
    {
        "name": "James Davis",
        "age": 57,
        "country": "BR"
    },
    {
        "name": "Mr. David Kemp",
        "age": 40,
        "country": "CA"
    },
    {
        "name": "Barbara Price",
        "age": 41,
        "country": "DE"
    },
    {
        "name": "Amanda Ward",
        "age": 24,
        "country": "CA"
    },
    {
        "name": "Gabriel Lynch",
        "age": 35,
        "country": "FR"
    },
    {
        "name": "Parker Lawrence",
        "age": 52,
        "country": "AU"
    },
    {
        "name": "Eddie Hill",
        "age": 33,
        "country": "US"
    },
    {
        "name": "Bethany Jenkins",
        "age": 38,
        "country": "BR"
    },
    {
        "name": "John Lambert",
        "age": 26,
        "country": "FR"
    },
    {
        "name": "Julia Mcmahon",
        "age": 23,
        "country": "CA"
    },
    {
        "name": "David Gonzalez",
        "age": 39,
        "country": "UK"
    },
    {
        "name": "Edwin Weber",
        "age": 31,
        "country": "FR"
    },
    {
        "name": "Dr. Aaron Taylor",
        "age": 28,
        "country": "BR"
    },
    {
        "name": "Paul Ross",
        "age": 46,
        "country": "FR"
    },
    {
        "name": "Donna Anderson",
        "age": 21,
        "country": "CA"
    },
    {
        "name": "Steven Anderson",
        "age": 37,
        "country": "AU"
    },
    {
        "name": "Briana Gomez",
        "age": 30,
        "country": "FR"
    },
    {
        "name": "Nancy Smith",
        "age": 18,
        "country": "BR"
    },
    {
        "name": "Brian Cruz",
        "age": 60,
        "country": "US"
    },
    {
        "name": "Howard Walker",
        "age": 55,
        "country": "CA"
    },
    {
        "name": "Justin West",
        "age": 44,
        "country": "US"
    },
    {
        "name": "Andrew Kemp",
        "age": 55,
        "country": "DE"
    },
    {
        "name": "Jeremy Phillips",
        "age": 43,
        "country": "UK"
    },
    {
        "name": "Aaron Edwards",
        "age": 42,
        "country": "UK"
    },
    {
        "name": "Angela Graves",
        "age": 31,
        "country": "DE"
    },
    {
        "name": "Stephanie Martinez",
        "age": 31,
        "country": "FR"
    },
    {
        "name": "Christine Haas",
        "age": 29,
        "country": "JP"
    },
    {
        "name": "James Johnson",
        "age": 55,
        "country": "JP"
    },
    {
        "name": "Shannon Kelley",
        "age": 50,
        "country": "JP"
    },
    {
        "name": "Mr. Garrett Bailey",
        "age": 44,
        "country": "US"
    },
    {
        "name": "Krista Johnson",
        "age": 49,
        "country": "DE"
    },
    {
        "name": "Tammy Brown",
        "age": 26,
        "country": "AU"
    },
    {
        "name": "Ashley Hardy",
        "age": 42,
        "country": "US"
    },
    {
        "name": "Tina King",
        "age": 31,
        "country": "CA"
    },
    {
        "name": "Hannah Hoover",
        "age": 28,
        "country": "DE"
    },
    {
        "name": "Julie Miller",
        "age": 20,
        "country": "JP"
    },
    {
        "name": "Stephanie Hamilton",
        "age": 50,
        "country": "BR"
    },
    {
        "name": "Jennifer Taylor",
        "age": 30,
        "country": "JP"
    },
    {
        "name": "Ariana Baker",
        "age": 50,
        "country": "CA"
    },
    {
        "name": "Terry Davila",
        "age": 60,
        "country": "AU"
    },
    {
        "name": "Daniel Harris",
        "age": 28,
        "country": "DE"
    },
    {
        "name": "Joseph Smith",
        "age": 48,
        "country": "US"
    },
    {
        "name": "Chelsea Ramirez",
        "age": 50,
        "country": "AU"
    },
    {
        "name": "Angela Nguyen",
        "age": 55,
        "country": "JP"
    },
    {
        "name": "Mathew Silva",
        "age": 22,
        "country": "BR"
    },
    {
        "name": "Pamela Wang",
        "age": 60,
        "country": "AU"
    },
    {
        "name": "Mark Garcia",
        "age": 42,
        "country": "DE"
    },
    {
        "name": "Christopher Pennington",
        "age": 32,
        "country": "US"
    },
    {
        "name": "Laurie Williams",
        "age": 49,
        "country": "AU"
    },
    {
        "name": "Stacey Mcfarland",
        "age": 45,
        "country": "UK"
    },
    {
        "name": "Christopher Miller",
        "age": 52,
        "country": "BR"
    },
    {
        "name": "Adriana Hawkins",
        "age": 42,
        "country": "AU"
    },
    {
        "name": "Nicholas Webster",
        "age": 51,
        "country": "US"
    },
    {
        "name": "Christine Anderson",
        "age": 59,
        "country": "UK"
    },
    {
        "name": "Kathy Wolfe",
        "age": 48,
        "country": "DE"
    },
    {
        "name": "Stephanie Hall",
        "age": 18,
        "country": "CA"
    },
    {
        "name": "James Allen",
        "age": 43,
        "country": "FR"
    },
    {
        "name": "Roger Mcbride",
        "age": 28,
        "country": "BR"
    },
    {
        "name": "Steven Woodward",
        "age": 36,
        "country": "CA"
    },
    {
        "name": "Charles Sanford",
        "age": 38,
        "country": "AU"
    },
    {
        "name": "Karen Herrera",
        "age": 36,
        "country": "JP"
    },
    {
        "name": "Jasmine Gardner",
        "age": 49,
        "country": "JP"
    },
    {
        "name": "Alison Lewis",
        "age": 42,
        "country": "BR"
    },
    {
        "name": "Matthew Freeman",
        "age": 60,
        "country": "UK"
    },
    {
        "name": "Andrea Greer",
        "age": 55,
        "country": "BR"
    },
    {
        "name": "Daryl Burton",
        "age": 47,
        "country": "JP"
    },
    {
        "name": "John Gilbert",
        "age": 42,
        "country": "FR"
    },
    {
        "name": "Jessica Golden",
        "age": 37,
        "country": "UK"
    },
    {
        "name": "Dana Goodman",
        "age": 40,
        "country": "CA"
    },
    {
        "name": "Billy Clarke",
        "age": 43,
        "country": "FR"
    },
    {
        "name": "Cristian Miller",
        "age": 21,
        "country": "CA"
    },
    {
        "name": "Cody Lewis",
        "age": 45,
        "country": "UK"
    },
    {
        "name": "William Perez",
        "age": 20,
        "country": "BR"
    },
    {
        "name": "Elizabeth Fox",
        "age": 49,
        "country": "FR"
    },
    {
        "name": "Angela Martin",
        "age": 60,
        "country": "BR"
    },
    {
        "name": "Jeanette Sherman",
        "age": 46,
        "country": "DE"
    },
    {
        "name": "Joseph Coleman",
        "age": 55,
        "country": "UK"
    },
    {
        "name": "Gary Smith",
        "age": 40,
        "country": "BR"
    },
    {
        "name": "Albert Martin",
        "age": 24,
        "country": "UK"
    },
    {
        "name": "Bernard Martin",
        "age": 41,
        "country": "DE"
    },
    {
        "name": "Tyler Pitts",
        "age": 26,
        "country": "US"
    },
    {
        "name": "Robert Patel",
        "age": 28,
        "country": "CA"
    },
    {
        "name": "April Hendrix",
        "age": 59,
        "country": "AU"
    },
    {
        "name": "Anne Tate",
        "age": 31,
        "country": "FR"
    },
    {
        "name": "Margaret Cline",
        "age": 58,
        "country": "US"
    },
    {
        "name": "Monica Vazquez",
        "age": 19,
        "country": "DE"
    },
    {
        "name": "Amanda Esparza",
        "age": 30,
        "country": "AU"
    },
    {
        "name": "Kimberly Lane",
        "age": 31,
        "country": "UK"
    },
    {
        "name": "Taylor Curry",
        "age": 21,
        "country": "DE"
    },
    {
        "name": "Michael Calderon",
        "age": 22,
        "country": "DE"
    },
    {
        "name": "Dennis Salas",
        "age": 38,
        "country": "UK"
    },
    {
        "name": "Dale Bowman",
        "age": 20,
        "country": "JP"
    },
    {
        "name": "Michael Chen",
        "age": 38,
        "country": "AU"
    },
    {
        "name": "Sara Burns",
        "age": 34,
        "country": "DE"
    },
    {
        "name": "Melissa Collins",
        "age": 25,
        "country": "DE"
    },
    {
        "name": "Morgan Clark",
        "age": 48,
        "country": "FR"
    },
    {
        "name": "Charles Thomas",
        "age": 54,
        "country": "DE"
    },
    {
        "name": "Jeffery Davis",
        "age": 27,
        "country": "AU"
    },
    {
        "name": "William Sosa",
        "age": 46,
        "country": "AU"
    },
    {
        "name": "Ross Collins",
        "age": 53,
        "country": "JP"
    },
    {
        "name": "Eric Glass",
        "age": 37,
        "country": "JP"
    },
    {
        "name": "Robert Flores",
        "age": 30,
        "country": "US"
    },
    {
        "name": "Catherine Brown",
        "age": 45,
        "country": "AU"
    },
    {
        "name": "Jessica Mcbride",
        "age": 54,
        "country": "UK"
    },
    {
        "name": "Dana Thomas",
        "age": 24,
        "country": "DE"
    },
    {
        "name": "Patricia Mendoza",
        "age": 41,
        "country": "UK"
    },
    {
        "name": "Victoria Hensley",
        "age": 51,
        "country": "FR"
    },
    {
        "name": "Brian Sloan",
        "age": 55,
        "country": "DE"
    },
    {
        "name": "Marissa Gray",
        "age": 48,
        "country": "US"
    },
    {
        "name": "Anthony Martin",
        "age": 52,
        "country": "FR"
    },
    {
        "name": "Taylor Jordan",
        "age": 57,
        "country": "UK"
    },
    {
        "name": "Jeffrey Campbell",
        "age": 42,
        "country": "DE"
    },
    {
        "name": "Jacob Marquez",
        "age": 33,
        "country": "AU"
    },
    {
        "name": "Andrea Blair",
        "age": 31,
        "country": "US"
    },
    {
        "name": "Todd Price",
        "age": 53,
        "country": "AU"
    },
    {
        "name": "Calvin Hatfield Jr.",
        "age": 30,
        "country": "CA"
    },
    {
        "name": "Sarah Higgins",
        "age": 34,
        "country": "AU"
    },
    {
        "name": "George Smith III",
        "age": 27,
        "country": "BR"
    },
    {
        "name": "Deanna Gonzales",
        "age": 33,
        "country": "US"
    },
    {
        "name": "Timothy Jackson",
        "age": 22,
        "country": "BR"
    },
    {
        "name": "Dennis Chambers",
        "age": 34,
        "country": "BR"
    },
    {
        "name": "Tony Anderson",
        "age": 38,
        "country": "US"
    },
    {
        "name": "Kristen Davis",
        "age": 58,
        "country": "FR"
    },
    {
        "name": "Jody Roberson",
        "age": 38,
        "country": "FR"
    },
    {
        "name": "Katherine Carr",
        "age": 35,
        "country": "AU"
    },
    {
        "name": "Kyle Johnson",
        "age": 46,
        "country": "AU"
    },
    {
        "name": "Kellie Love",
        "age": 28,
        "country": "UK"
    },
    {
        "name": "Debra Rivera",
        "age": 28,
        "country": "UK"
    },
    {
        "name": "Samantha Colon",
        "age": 20,
        "country": "US"
    },
    {
        "name": "Andrew Choi",
        "age": 43,
        "country": "FR"
    },
    {
        "name": "Juan Garcia",
        "age": 18,
        "country": "BR"
    },
    {
        "name": "Kimberly Williams",
        "age": 33,
        "country": "FR"
    },
    {
        "name": "Calvin Leon",
        "age": 27,
        "country": "FR"
    },
    {
        "name": "Laura Davis",
        "age": 23,
        "country": "US"
    },
    {
        "name": "Alan Griffith",
        "age": 55,
        "country": "BR"
    },
    {
        "name": "Jennifer Perry",
        "age": 29,
        "country": "DE"
    },
    {
        "name": "Scott Choi",
        "age": 25,
        "country": "DE"
    },
    {
        "name": "Daniel Smith",
        "age": 39,
        "country": "BR"
    },
    {
        "name": "Daniel Cooke",
        "age": 34,
        "country": "CA"
    },
    {
        "name": "Elizabeth Moore",
        "age": 51,
        "country": "FR"
    },
    {
        "name": "Shaun Phillips",
        "age": 24,
        "country": "US"
    },
    {
        "name": "Michelle Hall",
        "age": 43,
        "country": "US"
    },
    {
        "name": "John Chandler",
        "age": 46,
        "country": "UK"
    },
    {
        "name": "Kevin Alexander",
        "age": 38,
        "country": "FR"
    },
    {
        "name": "Jeffrey Garcia",
        "age": 57,
        "country": "BR"
    },
    {
        "name": "Elizabeth Little",
        "age": 43,
        "country": "JP"
    },
    {
        "name": "Briana Johnson",
        "age": 48,
        "country": "AU"
    },
    {
        "name": "Cristina Alexander",
        "age": 26,
        "country": "JP"
    },
    {
        "name": "Jennifer Shelton",
        "age": 22,
        "country": "FR"
    },
    {
        "name": "Cory Lee PhD",
        "age": 27,
        "country": "DE"
    },
    {
        "name": "Melissa Davis",
        "age": 47,
        "country": "AU"
    },
    {
        "name": "Amy Reed",
        "age": 52,
        "country": "FR"
    },
    {
        "name": "Sheila Shaffer",
        "age": 55,
        "country": "JP"
    },
    {
        "name": "David James",
        "age": 24,
        "country": "DE"
    },
    {
        "name": "Jack Alexander",
        "age": 60,
        "country": "AU"
    },
    {
        "name": "Vanessa Gonzales",
        "age": 19,
        "country": "AU"
    },
    {
        "name": "Dustin Bishop",
        "age": 49,
        "country": "BR"
    },
    {
        "name": "Bonnie Butler",
        "age": 47,
        "country": "CA"
    },
    {
        "name": "Willie Lopez",
        "age": 26,
        "country": "US"
    },
    {
        "name": "Breanna Nelson",
        "age": 18,
        "country": "UK"
    },
    {
        "name": "Sarah Ortiz",
        "age": 27,
        "country": "AU"
    },
    {
        "name": "Joel Rodriguez",
        "age": 23,
        "country": "BR"
    },
    {
        "name": "Tiffany Johnson DDS",
        "age": 46,
        "country": "UK"
    },
    {
        "name": "Brian Stephenson",
        "age": 46,
        "country": "JP"
    },
    {
        "name": "Ryan Banks",
        "age": 39,
        "country": "DE"
    },
    {
        "name": "Kristen Mendez",
        "age": 53,
        "country": "US"
    },
    {
        "name": "Howard Haynes",
        "age": 49,
        "country": "UK"
    },
    {
        "name": "Nicholas Mcguire",
        "age": 43,
        "country": "FR"
    },
    {
        "name": "Michael Miller",
        "age": 60,
        "country": "FR"
    },
    {
        "name": "Jesus Coleman",
        "age": 57,
        "country": "JP"
    },
    {
        "name": "Tara Bird",
        "age": 30,
        "country": "BR"
    },
    {
        "name": "Mark Lopez",
        "age": 24,
        "country": "JP"
    },
    {
        "name": "Gary Nunez",
        "age": 46,
        "country": "AU"
    },
    {
        "name": "Jennifer Nguyen",
        "age": 53,
        "country": "FR"
    },
    {
        "name": "Jessica Turner",
        "age": 25,
        "country": "BR"
    },
    {
        "name": "Joseph Warren",
        "age": 60,
        "country": "FR"
    },
    {
        "name": "Barbara Bryan",
        "age": 56,
        "country": "DE"
    },
    {
        "name": "Alexandra Williams",
        "age": 52,
        "country": "US"
    },
    {
        "name": "James Johnston",
        "age": 24,
        "country": "FR"
    },
    {
        "name": "Betty Gardner",
        "age": 27,
        "country": "UK"
    },
    {
        "name": "James Hurley",
        "age": 56,
        "country": "JP"
    },
    {
        "name": "Victoria Jordan",
        "age": 54,
        "country": "DE"
    },
    {
        "name": "Cory Buck",
        "age": 54,
        "country": "AU"
    },
    {
        "name": "Kevin Campbell",
        "age": 21,
        "country": "US"
    },
    {
        "name": "Bryan Phillips",
        "age": 18,
        "country": "US"
    },
    {
        "name": "Sean Hardy",
        "age": 32,
        "country": "JP"
    },
    {
        "name": "Margaret Sharp",
        "age": 27,
        "country": "FR"
    },
    {
        "name": "Bethany Wallace",
        "age": 28,
        "country": "FR"
    },
    {
        "name": "Douglas Hall",
        "age": 44,
        "country": "FR"
    },
    {
        "name": "Grant Kim",
        "age": 22,
        "country": "BR"
    },
    {
        "name": "Alyssa Coleman",
        "age": 51,
        "country": "AU"
    },
    {
        "name": "Lindsey Quinn",
        "age": 29,
        "country": "UK"
    },
    {
        "name": "Shawn Collins",
        "age": 30,
        "country": "BR"
    },
    {
        "name": "Lisa Obrien",
        "age": 19,
        "country": "JP"
    },
    {
        "name": "Dillon Chaney",
        "age": 48,
        "country": "BR"
    },
    {
        "name": "Sherry Herring",
        "age": 37,
        "country": "CA"
    },
    {
        "name": "Cynthia Flores",
        "age": 30,
        "country": "US"
    },
    {
        "name": "Eric White",
        "age": 51,
        "country": "FR"
    },
    {
        "name": "Walter Parker",
        "age": 59,
        "country": "US"
    },
    {
        "name": "Sarah Figueroa",
        "age": 42,
        "country": "FR"
    },
    {
        "name": "Maria Monroe",
        "age": 46,
        "country": "FR"
    },
    {
        "name": "Jordan Torres",
        "age": 48,
        "country": "UK"
    },
    {
        "name": "Robert Thompson",
        "age": 32,
        "country": "JP"
    },
    {
        "name": "John Parker",
        "age": 36,
        "country": "BR"
    },
    {
        "name": "Francisco Bryan",
        "age": 24,
        "country": "BR"
    },
    {
        "name": "Mr. Gregory Adams",
        "age": 36,
        "country": "BR"
    },
    {
        "name": "Morgan Brown",
        "age": 29,
        "country": "CA"
    },
    {
        "name": "Megan Navarro",
        "age": 38,
        "country": "AU"
    },
    {
        "name": "Mr. Christopher Rodriguez Jr.",
        "age": 25,
        "country": "CA"
    },
    {
        "name": "Katherine Baker",
        "age": 25,
        "country": "US"
    },
    {
        "name": "Nathan Cook",
        "age": 42,
        "country": "BR"
    },
    {
        "name": "Travis Burns",
        "age": 42,
        "country": "CA"
    },
    {
        "name": "Vickie Moore",
        "age": 20,
        "country": "BR"
    },
    {
        "name": "Brianna Chang",
        "age": 21,
        "country": "CA"
    },
    {
        "name": "Aaron Greene",
        "age": 20,
        "country": "AU"
    },
    {
        "name": "Shannon Harris",
        "age": 50,
        "country": "BR"
    },
    {
        "name": "Robert Giles",
        "age": 49,
        "country": "BR"
    },
    {
        "name": "Joseph Sexton",
        "age": 58,
        "country": "UK"
    },
    {
        "name": "Peter Alexander",
        "age": 44,
        "country": "CA"
    },
    {
        "name": "Raymond Gonzales",
        "age": 54,
        "country": "AU"
    },
    {
        "name": "Sandra King",
        "age": 58,
        "country": "DE"
    },
    {
        "name": "Brianna Williams",
        "age": 60,
        "country": "UK"
    },
    {
        "name": "William Bailey",
        "age": 47,
        "country": "JP"
    },
    {
        "name": "Jason Wells",
        "age": 47,
        "country": "US"
    },
    {
        "name": "James Jones",
        "age": 59,
        "country": "AU"
    },
    {
        "name": "Matthew Davidson",
        "age": 42,
        "country": "JP"
    },
    {
        "name": "Bailey Stephenson",
        "age": 44,
        "country": "US"
    },
    {
        "name": "Malik Saunders",
        "age": 44,
        "country": "BR"
    },
    {
        "name": "Timothy Miranda",
        "age": 23,
        "country": "BR"
    },
    {
        "name": "Karen Reid",
        "age": 50,
        "country": "FR"
    },
    {
        "name": "Sarah Hill",
        "age": 47,
        "country": "JP"
    },
    {
        "name": "Timothy Wolf",
        "age": 24,
        "country": "DE"
    },
    {
        "name": "Phillip Rodriguez",
        "age": 38,
        "country": "CA"
    },
    {
        "name": "Janet Miller",
        "age": 39,
        "country": "AU"
    },
    {
        "name": "Laura Gibson",
        "age": 43,
        "country": "FR"
    },
    {
        "name": "John Bird",
        "age": 19,
        "country": "CA"
    },
    {
        "name": "Jill Sheppard",
        "age": 50,
        "country": "JP"
    },
    {
        "name": "Laura Gonzalez",
        "age": 39,
        "country": "JP"
    },
    {
        "name": "David Cruz",
        "age": 40,
        "country": "DE"
    },
    {
        "name": "Gloria Pierce",
        "age": 29,
        "country": "UK"
    },
    {
        "name": "Shawn Murillo",
        "age": 57,
        "country": "AU"
    },
    {
        "name": "Justin Holland",
        "age": 55,
        "country": "FR"
    },
    {
        "name": "Erik Thomas",
        "age": 18,
        "country": "US"
    },
    {
        "name": "Anthony Richard",
        "age": 56,
        "country": "BR"
    },
    {
        "name": "Riley Smith",
        "age": 47,
        "country": "FR"
    },
    {
        "name": "Jordan Carroll",
        "age": 25,
        "country": "BR"
    },
    {
        "name": "Patricia Decker",
        "age": 22,
        "country": "US"
    },
    {
        "name": "Christopher Russell",
        "age": 24,
        "country": "UK"
    },
    {
        "name": "Jacob Jones",
        "age": 18,
        "country": "BR"
    },
    {
        "name": "Amy Reid",
        "age": 44,
        "country": "AU"
    },
    {
        "name": "Kathleen Faulkner",
        "age": 54,
        "country": "US"
    },
    {
        "name": "Robert Tucker",
        "age": 57,
        "country": "CA"
    },
    {
        "name": "Michael Watts",
        "age": 30,
        "country": "UK"
    },
    {
        "name": "Abigail Greene",
        "age": 56,
        "country": "US"
    },
    {
        "name": "Steven Cardenas",
        "age": 25,
        "country": "DE"
    },
    {
        "name": "Mary Velasquez",
        "age": 27,
        "country": "DE"
    },
    {
        "name": "Adriana Grant",
        "age": 57,
        "country": "BR"
    },
    {
        "name": "James Carroll",
        "age": 32,
        "country": "CA"
    },
    {
        "name": "Shelly Sandoval",
        "age": 24,
        "country": "FR"
    },
    {
        "name": "Melissa Hall",
        "age": 34,
        "country": "BR"
    },
    {
        "name": "Christy Gonzalez",
        "age": 39,
        "country": "FR"
    },
    {
        "name": "Jordan Klein",
        "age": 48,
        "country": "BR"
    },
    {
        "name": "Erica Robinson",
        "age": 28,
        "country": "AU"
    },
    {
        "name": "Brian Johnson",
        "age": 55,
        "country": "DE"
    },
    {
        "name": "Gregory Baker",
        "age": 23,
        "country": "US"
    },
    {
        "name": "Jennifer Jensen",
        "age": 37,
        "country": "CA"
    },
    {
        "name": "Robert Johnson",
        "age": 19,
        "country": "CA"
    },
    {
        "name": "Robert Anderson",
        "age": 39,
        "country": "DE"
    },
    {
        "name": "Joseph Romero",
        "age": 27,
        "country": "CA"
    },
    {
        "name": "Christopher Gonzalez",
        "age": 29,
        "country": "AU"
    },
    {
        "name": "Kristina Rogers",
        "age": 49,
        "country": "US"
    },
    {
        "name": "Tiffany Williams",
        "age": 23,
        "country": "FR"
    },
    {
        "name": "Jill Brown",
        "age": 27,
        "country": "CA"
    },
    {
        "name": "Lynn Newton",
        "age": 42,
        "country": "FR"
    },
    {
        "name": "Alexander Freeman",
        "age": 42,
        "country": "UK"
    },
    {
        "name": "James Stephens",
        "age": 35,
        "country": "FR"
    },
    {
        "name": "Sheri Livingston",
        "age": 31,
        "country": "DE"
    },
    {
        "name": "Julie Rogers",
        "age": 39,
        "country": "US"
    },
    {
        "name": "Randy Armstrong",
        "age": 36,
        "country": "BR"
    },
    {
        "name": "Nathan Salazar",
        "age": 52,
        "country": "BR"
    },
    {
        "name": "Mandy Smith",
        "age": 51,
        "country": "DE"
    },
    {
        "name": "Ronnie Larsen",
        "age": 20,
        "country": "UK"
    },
    {
        "name": "Joseph Ford",
        "age": 51,
        "country": "US"
    },
    {
        "name": "Jacob Cole",
        "age": 27,
        "country": "FR"
    },
    {
        "name": "Ryan Davis",
        "age": 26,
        "country": "FR"
    },
    {
        "name": "Megan Carson",
        "age": 19,
        "country": "UK"
    },
    {
        "name": "Jordan Martin",
        "age": 53,
        "country": "UK"
    },
    {
        "name": "Gary Martin",
        "age": 38,
        "country": "AU"
    },
    {
        "name": "Mrs. Laura Rogers DDS",
        "age": 43,
        "country": "BR"
    },
    {
        "name": "Jamie Scott",
        "age": 45,
        "country": "DE"
    },
    {
        "name": "Rebecca White",
        "age": 32,
        "country": "FR"
    },
    {
        "name": "Kathy Powers",
        "age": 21,
        "country": "BR"
    },
    {
        "name": "Beverly Williams",
        "age": 52,
        "country": "AU"
    },
    {
        "name": "Christopher Lee",
        "age": 32,
        "country": "JP"
    },
    {
        "name": "Mitchell Brown",
        "age": 32,
        "country": "US"
    },
    {
        "name": "Ashley Myers",
        "age": 51,
        "country": "US"
    },
    {
        "name": "Dawn Benson",
        "age": 43,
        "country": "UK"
    },
    {
        "name": "Michael Gomez",
        "age": 24,
        "country": "US"
    },
    {
        "name": "Jessica Aguilar",
        "age": 31,
        "country": "FR"
    },
    {
        "name": "Aaron Goodwin",
        "age": 18,
        "country": "UK"
    },
    {
        "name": "Heather Weber",
        "age": 51,
        "country": "CA"
    },
    {
        "name": "Daniel Greer",
        "age": 55,
        "country": "UK"
    },
    {
        "name": "Aaron Stewart",
        "age": 46,
        "country": "UK"
    },
    {
        "name": "Bradley Curtis",
        "age": 29,
        "country": "AU"
    },
    {
        "name": "Katie Gonzalez",
        "age": 26,
        "country": "BR"
    },
    {
        "name": "Peter Kim",
        "age": 54,
        "country": "CA"
    },
    {
        "name": "Jade Johnson",
        "age": 45,
        "country": "JP"
    },
    {
        "name": "Derek Graves",
        "age": 23,
        "country": "AU"
    },
    {
        "name": "Mrs. Janice Roth",
        "age": 48,
        "country": "JP"
    },
    {
        "name": "Jimmy Thomas",
        "age": 20,
        "country": "BR"
    },
    {
        "name": "Kimberly Pierce",
        "age": 55,
        "country": "CA"
    },
    {
        "name": "William Smith",
        "age": 53,
        "country": "JP"
    },
    {
        "name": "David Ross",
        "age": 25,
        "country": "UK"
    },
    {
        "name": "Elizabeth Smith",
        "age": 57,
        "country": "AU"
    },
    {
        "name": "Rebecca Duran",
        "age": 46,
        "country": "FR"
    },
    {
        "name": "Laura Robinson",
        "age": 37,
        "country": "AU"
    },
    {
        "name": "Lori Todd",
        "age": 44,
        "country": "FR"
    },
    {
        "name": "Nicole Anthony",
        "age": 22,
        "country": "DE"
    },
    {
        "name": "Cynthia Carr",
        "age": 26,
        "country": "JP"
    },
    {
        "name": "Nancy Campos",
        "age": 29,
        "country": "UK"
    },
    {
        "name": "Hannah Hamilton",
        "age": 50,
        "country": "FR"
    },
    {
        "name": "Kristen Miller",
        "age": 39,
        "country": "BR"
    },
    {
        "name": "Joshua Coffey",
        "age": 24,
        "country": "US"
    },
    {
        "name": "Elizabeth Martin",
        "age": 37,
        "country": "AU"
    },
    {
        "name": "Jonathon Bradley",
        "age": 21,
        "country": "US"
    },
    {
        "name": "Keith Harris",
        "age": 32,
        "country": "UK"
    },
    {
        "name": "Anna Mcclain",
        "age": 26,
        "country": "DE"
    },
    {
        "name": "Karen Mendoza",
        "age": 44,
        "country": "JP"
    },
    {
        "name": "Laura Clark",
        "age": 49,
        "country": "BR"
    },
    {
        "name": "April Townsend",
        "age": 49,
        "country": "AU"
    },
    {
        "name": "Kim Gibson",
        "age": 37,
        "country": "DE"
    },
    {
        "name": "Beverly Simon",
        "age": 29,
        "country": "CA"
    },
    {
        "name": "Richard Hawkins",
        "age": 47,
        "country": "FR"
    },
    {
        "name": "Karen Martinez",
        "age": 59,
        "country": "UK"
    },
    {
        "name": "David Russell",
        "age": 47,
        "country": "CA"
    },
    {
        "name": "James Maldonado",
        "age": 21,
        "country": "JP"
    },
    {
        "name": "Brooke Galvan",
        "age": 28,
        "country": "US"
    },
    {
        "name": "William Ramsey",
        "age": 58,
        "country": "BR"
    },
    {
        "name": "Holly Ramirez",
        "age": 19,
        "country": "US"
    },
    {
        "name": "Dr. April Castaneda",
        "age": 57,
        "country": "CA"
    },
    {
        "name": "David White",
        "age": 31,
        "country": "CA"
    },
    {
        "name": "Daniel Gutierrez",
        "age": 53,
        "country": "FR"
    },
    {
        "name": "Donald Morgan",
        "age": 33,
        "country": "CA"
    },
    {
        "name": "Michael Stokes",
        "age": 36,
        "country": "AU"
    },
    {
        "name": "Deborah Sandoval",
        "age": 39,
        "country": "FR"
    },
    {
        "name": "Mary Watkins",
        "age": 42,
        "country": "US"
    },
    {
        "name": "Alexander Thompson",
        "age": 27,
        "country": "FR"
    },
    {
        "name": "Jordan Barrett",
        "age": 31,
        "country": "UK"
    },
    {
        "name": "Christina Lee",
        "age": 44,
        "country": "JP"
    },
    {
        "name": "Christie Clarke",
        "age": 20,
        "country": "AU"
    },
    {
        "name": "Jonathon Dixon",
        "age": 21,
        "country": "FR"
    },
    {
        "name": "Jerry Larsen",
        "age": 60,
        "country": "FR"
    },
    {
        "name": "Nicholas Montgomery",
        "age": 23,
        "country": "FR"
    },
    {
        "name": "Deanna Vaughn",
        "age": 24,
        "country": "FR"
    },
    {
        "name": "Christina Hill",
        "age": 30,
        "country": "AU"
    },
    {
        "name": "Michele Shah",
        "age": 30,
        "country": "AU"
    },
    {
        "name": "Nicole Johnson",
        "age": 52,
        "country": "BR"
    },
    {
        "name": "Scott Jones",
        "age": 52,
        "country": "US"
    },
    {
        "name": "Brandon Allen",
        "age": 53,
        "country": "FR"
    },
    {
        "name": "John Elliott",
        "age": 20,
        "country": "BR"
    },
    {
        "name": "Robert Lopez",
        "age": 22,
        "country": "BR"
    },
    {
        "name": "Ross Scott",
        "age": 60,
        "country": "JP"
    },
    {
        "name": "Lance Savage",
        "age": 22,
        "country": "JP"
    },
    {
        "name": "Mrs. Kelli Blackwell DVM",
        "age": 59,
        "country": "UK"
    },
    {
        "name": "Jessica Powell",
        "age": 59,
        "country": "US"
    },
    {
        "name": "Brenda Williams",
        "age": 32,
        "country": "DE"
    },
    {
        "name": "Charles Duncan",
        "age": 37,
        "country": "AU"
    },
    {
        "name": "Veronica George",
        "age": 23,
        "country": "AU"
    },
    {
        "name": "James Warren",
        "age": 42,
        "country": "JP"
    },
    {
        "name": "Colin Fuentes",
        "age": 44,
        "country": "US"
    },
    {
        "name": "Sarah Holland",
        "age": 22,
        "country": "AU"
    },
    {
        "name": "Lori Davidson",
        "age": 18,
        "country": "DE"
    },
    {
        "name": "Sharon Henry",
        "age": 32,
        "country": "CA"
    },
    {
        "name": "Lori Mayo",
        "age": 49,
        "country": "FR"
    },
    {
        "name": "Bryan Cox",
        "age": 59,
        "country": "UK"
    },
    {
        "name": "Donald Soto",
        "age": 26,
        "country": "AU"
    },
    {
        "name": "Lawrence Robertson",
        "age": 53,
        "country": "FR"
    },
    {
        "name": "Leslie Brown",
        "age": 19,
        "country": "DE"
    },
    {
        "name": "Jennifer Velasquez",
        "age": 52,
        "country": "AU"
    },
    {
        "name": "Joshua Roberts",
        "age": 26,
        "country": "AU"
    },
    {
        "name": "Lisa Walters",
        "age": 52,
        "country": "AU"
    },
    {
        "name": "Jacob Banks",
        "age": 58,
        "country": "JP"
    },
    {
        "name": "Donna Lopez",
        "age": 59,
        "country": "JP"
    },
    {
        "name": "Jason Stone",
        "age": 56,
        "country": "BR"
    },
    {
        "name": "Kevin Ayers",
        "age": 24,
        "country": "DE"
    },
    {
        "name": "Caroline Smith",
        "age": 23,
        "country": "JP"
    },
    {
        "name": "Richard Kim",
        "age": 24,
        "country": "UK"
    },
    {
        "name": "Dr. Christina Hayden",
        "age": 19,
        "country": "CA"
    },
    {
        "name": "Michelle Davis",
        "age": 54,
        "country": "JP"
    },
    {
        "name": "Todd Sanchez",
        "age": 26,
        "country": "BR"
    },
    {
        "name": "Derrick Weber",
        "age": 19,
        "country": "US"
    },
    {
        "name": "Scott Miller",
        "age": 49,
        "country": "UK"
    },
    {
        "name": "Luis Wagner",
        "age": 54,
        "country": "UK"
    },
    {
        "name": "Sheryl Collier",
        "age": 38,
        "country": "US"
    },
    {
        "name": "Aaron Jones",
        "age": 30,
        "country": "US"
    },
    {
        "name": "Curtis Moran",
        "age": 44,
        "country": "JP"
    },
    {
        "name": "James Martin",
        "age": 35,
        "country": "UK"
    },
    {
        "name": "Laura Hill",
        "age": 43,
        "country": "BR"
    },
    {
        "name": "Amy Wilson",
        "age": 59,
        "country": "FR"
    },
    {
        "name": "Alexis Watkins",
        "age": 40,
        "country": "CA"
    },
    {
        "name": "Mr. Donald Ward",
        "age": 40,
        "country": "US"
    },
    {
        "name": "Derek Jennings",
        "age": 35,
        "country": "BR"
    },
    {
        "name": "Linda Stewart",
        "age": 20,
        "country": "CA"
    },
    {
        "name": "Caitlyn Swanson",
        "age": 45,
        "country": "AU"
    },
    {
        "name": "Erica Terrell",
        "age": 28,
        "country": "FR"
    },
    {
        "name": "Christine Lee",
        "age": 42,
        "country": "UK"
    },
    {
        "name": "John Bishop",
        "age": 34,
        "country": "FR"
    },
    {
        "name": "Christopher Rivera",
        "age": 47,
        "country": "BR"
    },
    {
        "name": "William Spencer",
        "age": 44,
        "country": "BR"
    },
    {
        "name": "Amber Lee",
        "age": 39,
        "country": "BR"
    },
    {
        "name": "Kelly Jordan",
        "age": 47,
        "country": "JP"
    },
    {
        "name": "Sandra Clay",
        "age": 44,
        "country": "JP"
    },
    {
        "name": "Benjamin Brown",
        "age": 33,
        "country": "BR"
    },
    {
        "name": "Candice Williamson",
        "age": 25,
        "country": "BR"
    },
    {
        "name": "Anna Williamson",
        "age": 32,
        "country": "CA"
    },
    {
        "name": "Robert Ballard",
        "age": 42,
        "country": "AU"
    },
    {
        "name": "Charles Cline",
        "age": 43,
        "country": "DE"
    },
    {
        "name": "Suzanne House",
        "age": 58,
        "country": "JP"
    },
    {
        "name": "Christy Kaufman",
        "age": 45,
        "country": "AU"
    },
    {
        "name": "Brent Martin",
        "age": 36,
        "country": "DE"
    },
    {
        "name": "Bryan Davis",
        "age": 19,
        "country": "CA"
    },
    {
        "name": "Brian Snyder",
        "age": 35,
        "country": "AU"
    },
    {
        "name": "Andrew Williams",
        "age": 50,
        "country": "US"
    },
    {
        "name": "Michelle Boyd",
        "age": 57,
        "country": "FR"
    },
    {
        "name": "Kathleen Hunter",
        "age": 41,
        "country": "JP"
    },
    {
        "name": "John Jackson",
        "age": 54,
        "country": "US"
    },
    {
        "name": "Rachel Rodriguez",
        "age": 29,
        "country": "DE"
    },
    {
        "name": "Antonio Williams",
        "age": 23,
        "country": "JP"
    },
    {
        "name": "Christopher Jarvis",
        "age": 23,
        "country": "BR"
    },
    {
        "name": "Diane Ruiz MD",
        "age": 19,
        "country": "CA"
    },
    {
        "name": "Donald Cameron",
        "age": 28,
        "country": "AU"
    },
    {
        "name": "Stacey Morton",
        "age": 53,
        "country": "UK"
    },
    {
        "name": "Christine Avila",
        "age": 51,
        "country": "BR"
    },
    {
        "name": "Mary Daugherty",
        "age": 42,
        "country": "CA"
    },
    {
        "name": "Mrs. Madison Weaver DDS",
        "age": 59,
        "country": "AU"
    },
    {
        "name": "James Berry",
        "age": 32,
        "country": "FR"
    },
    {
        "name": "Tiffany Escobar",
        "age": 46,
        "country": "AU"
    },
    {
        "name": "Jackie Freeman",
        "age": 40,
        "country": "UK"
    },
    {
        "name": "Shannon Cruz",
        "age": 33,
        "country": "US"
    },
    {
        "name": "Bryan Pham",
        "age": 18,
        "country": "AU"
    },
    {
        "name": "Gerald Henderson",
        "age": 26,
        "country": "JP"
    },
    {
        "name": "William Humphrey",
        "age": 26,
        "country": "CA"
    },
    {
        "name": "Deborah Smith",
        "age": 31,
        "country": "DE"
    },
    {
        "name": "Kari Miller",
        "age": 47,
        "country": "DE"
    },
    {
        "name": "Stephanie Rivers",
        "age": 29,
        "country": "AU"
    },
    {
        "name": "Jonathan Thompson",
        "age": 53,
        "country": "UK"
    },
    {
        "name": "Angela Wilson",
        "age": 44,
        "country": "US"
    },
    {
        "name": "Michaela Villegas",
        "age": 55,
        "country": "AU"
    },
    {
        "name": "Mark Clay",
        "age": 23,
        "country": "BR"
    },
    {
        "name": "Tina Wilson",
        "age": 18,
        "country": "BR"
    },
    {
        "name": "Amanda Sutton",
        "age": 39,
        "country": "DE"
    },
    {
        "name": "Karen Buck",
        "age": 29,
        "country": "CA"
    },
    {
        "name": "Jennifer Park",
        "age": 55,
        "country": "FR"
    },
    {
        "name": "Pamela Murphy",
        "age": 31,
        "country": "CA"
    },
    {
        "name": "Michael Lopez MD",
        "age": 50,
        "country": "UK"
    },
    {
        "name": "Bridget Hess",
        "age": 25,
        "country": "BR"
    },
    {
        "name": "Valerie Christian",
        "age": 36,
        "country": "CA"
    },
    {
        "name": "Deanna Thomas",
        "age": 31,
        "country": "AU"
    },
    {
        "name": "Jeffery White",
        "age": 51,
        "country": "US"
    },
    {
        "name": "Angela Cooper",
        "age": 59,
        "country": "US"
    },
    {
        "name": "Melissa Andrews",
        "age": 46,
        "country": "FR"
    },
    {
        "name": "Leslie King",
        "age": 20,
        "country": "US"
    },
    {
        "name": "Jennifer Andrews",
        "age": 20,
        "country": "BR"
    },
    {
        "name": "Kathy Green",
        "age": 18,
        "country": "US"
    },
    {
        "name": "Kelsey Owen",
        "age": 24,
        "country": "DE"
    },
    {
        "name": "Melanie Christian",
        "age": 50,
        "country": "UK"
    },
    {
        "name": "Christine Edwards",
        "age": 30,
        "country": "FR"
    },
    {
        "name": "Marvin Gonzalez",
        "age": 38,
        "country": "AU"
    },
    {
        "name": "Amber Parsons",
        "age": 44,
        "country": "JP"
    },
    {
        "name": "Wanda Wilson",
        "age": 57,
        "country": "UK"
    },
    {
        "name": "Travis Schneider",
        "age": 24,
        "country": "JP"
    },
    {
        "name": "Kristen Parrish",
        "age": 33,
        "country": "CA"
    },
    {
        "name": "Bethany May",
        "age": 50,
        "country": "CA"
    },
    {
        "name": "Stephen Brock",
        "age": 53,
        "country": "UK"
    },
    {
        "name": "Danny Johnson",
        "age": 19,
        "country": "CA"
    },
    {
        "name": "Tony Clarke",
        "age": 43,
        "country": "JP"
    },
    {
        "name": "Mitchell Bowman",
        "age": 27,
        "country": "AU"
    },
    {
        "name": "Tim Taylor",
        "age": 20,
        "country": "BR"
    },
    {
        "name": "Ashlee Carson",
        "age": 24,
        "country": "US"
    },
    {
        "name": "Sarah Marshall MD",
        "age": 51,
        "country": "AU"
    },
    {
        "name": "Tracy White",
        "age": 44,
        "country": "DE"
    },
    {
        "name": "Sarah Brooks",
        "age": 38,
        "country": "JP"
    },
    {
        "name": "Michelle Horne",
        "age": 35,
        "country": "BR"
    },
    {
        "name": "Thomas Johnson",
        "age": 29,
        "country": "UK"
    },
    {
        "name": "Daniel Martin",
        "age": 33,
        "country": "AU"
    },
    {
        "name": "Adam Kelly",
        "age": 20,
        "country": "US"
    },
    {
        "name": "Heather Gillespie",
        "age": 43,
        "country": "BR"
    },
    {
        "name": "Andrew Moreno",
        "age": 24,
        "country": "DE"
    },
    {
        "name": "Michael Williams",
        "age": 48,
        "country": "CA"
    },
    {
        "name": "Trevor Booth",
        "age": 60,
        "country": "US"
    },
    {
        "name": "Matthew Gentry",
        "age": 36,
        "country": "US"
    },
    {
        "name": "Matthew Garcia",
        "age": 50,
        "country": "UK"
    },
    {
        "name": "Phillip Watson MD",
        "age": 51,
        "country": "BR"
    },
    {
        "name": "Clinton Diaz",
        "age": 40,
        "country": "AU"
    },
    {
        "name": "Terri Jackson",
        "age": 51,
        "country": "AU"
    },
    {
        "name": "Karina Boyer",
        "age": 43,
        "country": "DE"
    },
    {
        "name": "Lori Meyer PhD",
        "age": 42,
        "country": "US"
    },
    {
        "name": "Monica Evans",
        "age": 39,
        "country": "AU"
    },
    {
        "name": "Mary Erickson",
        "age": 55,
        "country": "DE"
    },
    {
        "name": "Melanie Lucas",
        "age": 48,
        "country": "JP"
    },
    {
        "name": "Angela Bates",
        "age": 31,
        "country": "UK"
    },
    {
        "name": "Ms. Angela Lyons",
        "age": 51,
        "country": "AU"
    },
    {
        "name": "Cory Brennan",
        "age": 30,
        "country": "US"
    },
    {
        "name": "Crystal Edwards",
        "age": 43,
        "country": "US"
    },
    {
        "name": "Donald Fletcher",
        "age": 24,
        "country": "DE"
    },
    {
        "name": "Michael Reese",
        "age": 31,
        "country": "CA"
    },
    {
        "name": "Kenneth Barr",
        "age": 33,
        "country": "FR"
    },
    {
        "name": "Emily Brown",
        "age": 49,
        "country": "UK"
    },
    {
        "name": "Douglas Sutton",
        "age": 55,
        "country": "JP"
    },
    {
        "name": "Laura Griffith",
        "age": 26,
        "country": "AU"
    },
    {
        "name": "Jaime Cooper",
        "age": 19,
        "country": "BR"
    },
    {
        "name": "Jessica Robertson",
        "age": 20,
        "country": "JP"
    },
    {
        "name": "Veronica Silva",
        "age": 35,
        "country": "CA"
    },
    {
        "name": "Brandon Terry",
        "age": 43,
        "country": "US"
    },
    {
        "name": "Dennis Edwards",
        "age": 20,
        "country": "UK"
    },
    {
        "name": "Carrie Morris",
        "age": 46,
        "country": "BR"
    },
    {
        "name": "James Miller",
        "age": 39,
        "country": "FR"
    },
    {
        "name": "Joseph Garner",
        "age": 41,
        "country": "UK"
    },
    {
        "name": "John Jensen",
        "age": 41,
        "country": "UK"
    },
    {
        "name": "David Mullins",
        "age": 31,
        "country": "US"
    },
    {
        "name": "Nancy Blankenship",
        "age": 59,
        "country": "US"
    },
    {
        "name": "Philip Anderson",
        "age": 50,
        "country": "DE"
    },
    {
        "name": "Nicholas Jackson",
        "age": 25,
        "country": "US"
    },
    {
        "name": "Gina Green",
        "age": 35,
        "country": "CA"
    },
    {
        "name": "Annette Clements",
        "age": 51,
        "country": "BR"
    },
    {
        "name": "Samantha Horton",
        "age": 54,
        "country": "CA"
    },
    {
        "name": "Christian Choi",
        "age": 47,
        "country": "JP"
    },
    {
        "name": "Kylie Ochoa",
        "age": 56,
        "country": "CA"
    },
    {
        "name": "Thomas Jenkins",
        "age": 59,
        "country": "US"
    },
    {
        "name": "Arthur Duncan",
        "age": 55,
        "country": "AU"
    },
    {
        "name": "Jennifer Anderson",
        "age": 34,
        "country": "DE"
    },
    {
        "name": "Gerald Werner Jr.",
        "age": 49,
        "country": "AU"
    },
    {
        "name": "Kelsey Scott",
        "age": 40,
        "country": "BR"
    },
    {
        "name": "Jose Jackson",
        "age": 42,
        "country": "FR"
    },
    {
        "name": "Dominic Goodwin",
        "age": 32,
        "country": "CA"
    },
    {
        "name": "Joseph King",
        "age": 32,
        "country": "JP"
    },
    {
        "name": "Mark Greer",
        "age": 40,
        "country": "US"
    },
    {
        "name": "Darrell Turner",
        "age": 41,
        "country": "DE"
    },
    {
        "name": "Richard Roth",
        "age": 32,
        "country": "DE"
    },
    {
        "name": "Jennifer Smith",
        "age": 57,
        "country": "JP"
    },
    {
        "name": "Alexander Mcgee",
        "age": 44,
        "country": "US"
    },
    {
        "name": "Ronald Anderson",
        "age": 50,
        "country": "CA"
    },
    {
        "name": "Gary Martin",
        "age": 52,
        "country": "US"
    },
    {
        "name": "Courtney Ortega",
        "age": 50,
        "country": "JP"
    },
    {
        "name": "Lori Young",
        "age": 31,
        "country": "AU"
    },
    {
        "name": "Scott Scott",
        "age": 41,
        "country": "DE"
    },
    {
        "name": "Lisa Garcia",
        "age": 43,
        "country": "CA"
    },
    {
        "name": "Stephen Thompson",
        "age": 26,
        "country": "DE"
    },
    {
        "name": "Anthony Wilson",
        "age": 49,
        "country": "US"
    },
    {
        "name": "Charles Lane",
        "age": 35,
        "country": "BR"
    },
    {
        "name": "Cory Martinez",
        "age": 50,
        "country": "US"
    },
    {
        "name": "Elizabeth Nichols",
        "age": 58,
        "country": "US"
    },
    {
        "name": "Jamie Flores",
        "age": 59,
        "country": "UK"
    },
    {
        "name": "Angela Fisher",
        "age": 44,
        "country": "US"
    },
    {
        "name": "Jessica Mckee",
        "age": 40,
        "country": "UK"
    },
    {
        "name": "Brian Phillips",
        "age": 26,
        "country": "US"
    },
    {
        "name": "John Fox",
        "age": 59,
        "country": "FR"
    },
    {
        "name": "Stacey Smith",
        "age": 22,
        "country": "FR"
    },
    {
        "name": "James Maddox",
        "age": 48,
        "country": "CA"
    },
    {
        "name": "Caitlin Thomas",
        "age": 39,
        "country": "JP"
    },
    {
        "name": "Daniel Soto",
        "age": 29,
        "country": "FR"
    },
    {
        "name": "Kathleen Barrett",
        "age": 51,
        "country": "UK"
    },
    {
        "name": "Patricia Bradley",
        "age": 59,
        "country": "DE"
    },
    {
        "name": "Terry Flores",
        "age": 23,
        "country": "FR"
    },
    {
        "name": "Todd Brewer",
        "age": 54,
        "country": "AU"
    },
    {
        "name": "Arthur Pierce",
        "age": 24,
        "country": "UK"
    },
    {
        "name": "Peter Garcia",
        "age": 36,
        "country": "FR"
    },
    {
        "name": "Tamara Andrews",
        "age": 53,
        "country": "US"
    },
    {
        "name": "Craig Dorsey",
        "age": 50,
        "country": "JP"
    },
    {
        "name": "Aaron Zhang",
        "age": 44,
        "country": "FR"
    },
    {
        "name": "Alexander Simpson",
        "age": 50,
        "country": "CA"
    },
    {
        "name": "Cody Collins",
        "age": 24,
        "country": "UK"
    },
    {
        "name": "Kirsten Brooks MD",
        "age": 47,
        "country": "FR"
    },
    {
        "name": "Hannah Garcia MD",
        "age": 23,
        "country": "AU"
    },
    {
        "name": "Marisa Rose",
        "age": 33,
        "country": "CA"
    },
    {
        "name": "Erin Roberson",
        "age": 46,
        "country": "JP"
    },
    {
        "name": "Lisa Sanchez",
        "age": 37,
        "country": "US"
    },
    {
        "name": "Jim Bishop",
        "age": 40,
        "country": "UK"
    },
    {
        "name": "Matthew Haas",
        "age": 50,
        "country": "US"
    },
    {
        "name": "Tracy Johnson PhD",
        "age": 35,
        "country": "US"
    },
    {
        "name": "James Hall",
        "age": 45,
        "country": "AU"
    },
    {
        "name": "Joseph Anderson PhD",
        "age": 20,
        "country": "UK"
    },
    {
        "name": "Pamela Perez",
        "age": 55,
        "country": "UK"
    },
    {
        "name": "Janice Rodriguez",
        "age": 51,
        "country": "AU"
    },
    {
        "name": "Allison Francis",
        "age": 19,
        "country": "BR"
    },
    {
        "name": "Alex Scott",
        "age": 18,
        "country": "DE"
    },
    {
        "name": "Parker Davis",
        "age": 54,
        "country": "DE"
    },
    {
        "name": "Julie Miller",
        "age": 29,
        "country": "US"
    },
    {
        "name": "Lauren House",
        "age": 50,
        "country": "US"
    },
    {
        "name": "Deanna James",
        "age": 26,
        "country": "CA"
    },
    {
        "name": "Lisa Adams",
        "age": 35,
        "country": "CA"
    },
    {
        "name": "Michael Dunn",
        "age": 20,
        "country": "AU"
    },
    {
        "name": "David Parsons",
        "age": 56,
        "country": "AU"
    },
    {
        "name": "Austin Terry",
        "age": 42,
        "country": "FR"
    },
    {
        "name": "Justin Cruz",
        "age": 33,
        "country": "AU"
    },
    {
        "name": "Jessica Hardy",
        "age": 37,
        "country": "BR"
    },
    {
        "name": "Christopher Stevenson",
        "age": 34,
        "country": "FR"
    },
    {
        "name": "Robert Medina",
        "age": 59,
        "country": "UK"
    },
    {
        "name": "Dillon Gutierrez",
        "age": 49,
        "country": "AU"
    },
    {
        "name": "Julie Romero",
        "age": 47,
        "country": "US"
    },
    {
        "name": "Anthony Chase",
        "age": 55,
        "country": "DE"
    },
    {
        "name": "Brandon Figueroa",
        "age": 35,
        "country": "CA"
    },
    {
        "name": "Kristie Anderson",
        "age": 32,
        "country": "UK"
    },
    {
        "name": "Amy Carpenter",
        "age": 24,
        "country": "UK"
    },
    {
        "name": "Stephen Fox",
        "age": 23,
        "country": "BR"
    },
    {
        "name": "Scott Williams",
        "age": 59,
        "country": "JP"
    },
    {
        "name": "Courtney Jones",
        "age": 24,
        "country": "DE"
    },
    {
        "name": "John Daugherty",
        "age": 40,
        "country": "CA"
    },
    {
        "name": "Mr. Carl Anderson",
        "age": 60,
        "country": "DE"
    },
    {
        "name": "Kelly Lewis",
        "age": 55,
        "country": "AU"
    },
    {
        "name": "Elizabeth Hall",
        "age": 25,
        "country": "DE"
    },
    {
        "name": "Christina Peterson",
        "age": 38,
        "country": "JP"
    },
    {
        "name": "Michael Miller",
        "age": 36,
        "country": "FR"
    },
    {
        "name": "Morgan Watts",
        "age": 47,
        "country": "US"
    },
    {
        "name": "Caitlin Romero",
        "age": 41,
        "country": "CA"
    },
    {
        "name": "Eric Hughes",
        "age": 20,
        "country": "JP"
    },
    {
        "name": "Gavin Blankenship",
        "age": 39,
        "country": "UK"
    },
    {
        "name": "Mark Lewis",
        "age": 44,
        "country": "AU"
    },
    {
        "name": "Mr. Benjamin Ramsey",
        "age": 54,
        "country": "US"
    },
    {
        "name": "John Arellano",
        "age": 49,
        "country": "FR"
    },
    {
        "name": "Todd Franklin",
        "age": 22,
        "country": "JP"
    },
    {
        "name": "Paul Odonnell",
        "age": 49,
        "country": "UK"
    },
    {
        "name": "Kevin Brown",
        "age": 60,
        "country": "JP"
    },
    {
        "name": "Karen Smith",
        "age": 51,
        "country": "AU"
    },
    {
        "name": "Elizabeth Wu",
        "age": 60,
        "country": "DE"
    },
    {
        "name": "Kathleen Stewart",
        "age": 54,
        "country": "BR"
    },
    {
        "name": "Jennifer Scott",
        "age": 19,
        "country": "AU"
    },
    {
        "name": "Scott Tanner",
        "age": 21,
        "country": "DE"
    },
    {
        "name": "Amanda Thompson",
        "age": 55,
        "country": "CA"
    },
    {
        "name": "Christopher Christensen",
        "age": 53,
        "country": "JP"
    },
    {
        "name": "Katrina Hebert",
        "age": 34,
        "country": "CA"
    },
    {
        "name": "Timothy Lopez",
        "age": 41,
        "country": "US"
    },
    {
        "name": "Mary Rodriguez",
        "age": 25,
        "country": "BR"
    },
    {
        "name": "Arthur Acevedo",
        "age": 55,
        "country": "US"
    },
    {
        "name": "Nathan Wells",
        "age": 57,
        "country": "DE"
    },
    {
        "name": "Marcus Jarvis",
        "age": 46,
        "country": "DE"
    },
    {
        "name": "Joshua Davis",
        "age": 33,
        "country": "BR"
    },
    {
        "name": "Darlene Burns",
        "age": 47,
        "country": "JP"
    },
    {
        "name": "David Horton",
        "age": 26,
        "country": "CA"
    },
    {
        "name": "Mr. Darrell Lewis",
        "age": 28,
        "country": "UK"
    },
    {
        "name": "Edwin Adams",
        "age": 32,
        "country": "AU"
    },
    {
        "name": "Ashley Villanueva",
        "age": 21,
        "country": "US"
    },
    {
        "name": "Jared Christensen",
        "age": 31,
        "country": "UK"
    },
    {
        "name": "George Kim",
        "age": 22,
        "country": "BR"
    },
    {
        "name": "Chad Jones",
        "age": 55,
        "country": "FR"
    },
    {
        "name": "Aaron Jackson",
        "age": 25,
        "country": "CA"
    },
    {
        "name": "James Willis",
        "age": 22,
        "country": "JP"
    },
    {
        "name": "Kevin Everett",
        "age": 31,
        "country": "AU"
    },
    {
        "name": "Anne Lynn",
        "age": 44,
        "country": "US"
    },
    {
        "name": "David Herrera",
        "age": 27,
        "country": "JP"
    },
    {
        "name": "Heather Cole",
        "age": 47,
        "country": "AU"
    },
    {
        "name": "Robert Woodward",
        "age": 35,
        "country": "AU"
    },
    {
        "name": "William Kim",
        "age": 55,
        "country": "DE"
    },
    {
        "name": "Lauren Fuller",
        "age": 28,
        "country": "FR"
    },
    {
        "name": "Julie Martin",
        "age": 46,
        "country": "FR"
    },
    {
        "name": "Cameron Smith",
        "age": 27,
        "country": "BR"
    },
    {
        "name": "Mark Thomas",
        "age": 36,
        "country": "DE"
    },
    {
        "name": "Erica Nguyen",
        "age": 53,
        "country": "JP"
    },
    {
        "name": "David Powell",
        "age": 44,
        "country": "BR"
    },
    {
        "name": "Samantha Jackson",
        "age": 21,
        "country": "US"
    },
    {
        "name": "Jason Campos",
        "age": 43,
        "country": "US"
    },
    {
        "name": "Terrence Watson",
        "age": 30,
        "country": "CA"
    },
    {
        "name": "Daniel Adams",
        "age": 21,
        "country": "BR"
    },
    {
        "name": "Jason Sandoval",
        "age": 43,
        "country": "BR"
    },
    {
        "name": "Michelle Hawkins",
        "age": 30,
        "country": "JP"
    },
    {
        "name": "Tracy Brown",
        "age": 56,
        "country": "AU"
    },
    {
        "name": "Christine Stevens",
        "age": 37,
        "country": "FR"
    },
    {
        "name": "Katherine White",
        "age": 39,
        "country": "JP"
    },
    {
        "name": "Kristopher Jordan",
        "age": 36,
        "country": "AU"
    },
    {
        "name": "Teresa Crawford",
        "age": 34,
        "country": "UK"
    },
    {
        "name": "Scott Sparks",
        "age": 32,
        "country": "AU"
    },
    {
        "name": "Mary Moore",
        "age": 25,
        "country": "JP"
    },
    {
        "name": "Jonathan Oliver",
        "age": 26,
        "country": "US"
    },
    {
        "name": "Kevin Gentry",
        "age": 22,
        "country": "AU"
    },
    {
        "name": "Sherry Crane",
        "age": 39,
        "country": "US"
    },
    {
        "name": "Stephen Thornton",
        "age": 35,
        "country": "JP"
    },
    {
        "name": "Mr. Matthew Lewis Jr.",
        "age": 43,
        "country": "AU"
    },
    {
        "name": "Victoria Delacruz",
        "age": 49,
        "country": "DE"
    },
    {
        "name": "Amanda Blankenship",
        "age": 51,
        "country": "DE"
    },
    {
        "name": "Jorge Rodriguez",
        "age": 56,
        "country": "UK"
    },
    {
        "name": "John Munoz",
        "age": 59,
        "country": "CA"
    },
    {
        "name": "Krista Mckay",
        "age": 55,
        "country": "DE"
    },
    {
        "name": "Timothy Peterson",
        "age": 30,
        "country": "JP"
    },
    {
        "name": "John Chase",
        "age": 43,
        "country": "UK"
    },
    {
        "name": "Marissa Munoz",
        "age": 37,
        "country": "DE"
    },
    {
        "name": "Suzanne Cook",
        "age": 25,
        "country": "UK"
    },
    {
        "name": "Alex Powers",
        "age": 33,
        "country": "CA"
    },
    {
        "name": "Kayla Mendoza",
        "age": 24,
        "country": "US"
    },
    {
        "name": "Adrian Martin",
        "age": 29,
        "country": "UK"
    },
    {
        "name": "Michael Bauer",
        "age": 51,
        "country": "JP"
    },
    {
        "name": "Stacey Hardin",
        "age": 54,
        "country": "UK"
    },
    {
        "name": "Ellen Carpenter",
        "age": 54,
        "country": "DE"
    },
    {
        "name": "Christian Riggs",
        "age": 52,
        "country": "JP"
    },
    {
        "name": "Michael Woods",
        "age": 59,
        "country": "JP"
    },
    {
        "name": "James Anderson",
        "age": 50,
        "country": "AU"
    },
    {
        "name": "David Reynolds",
        "age": 19,
        "country": "UK"
    },
    {
        "name": "John Flowers",
        "age": 18,
        "country": "FR"
    },
    {
        "name": "Melissa Hunter",
        "age": 31,
        "country": "CA"
    },
    {
        "name": "Justin Evans",
        "age": 57,
        "country": "BR"
    },
    {
        "name": "Travis Olson",
        "age": 58,
        "country": "DE"
    },
    {
        "name": "Steven Martin",
        "age": 34,
        "country": "JP"
    },
    {
        "name": "Melissa Miller",
        "age": 32,
        "country": "DE"
    },
    {
        "name": "Robin Cannon",
        "age": 46,
        "country": "BR"
    },
    {
        "name": "Dana Wade",
        "age": 38,
        "country": "AU"
    },
    {
        "name": "Kevin Hebert",
        "age": 25,
        "country": "DE"
    },
    {
        "name": "Abigail Franklin",
        "age": 60,
        "country": "JP"
    },
    {
        "name": "Nathan Stephenson",
        "age": 49,
        "country": "FR"
    },
    {
        "name": "Jacob Allen",
        "age": 45,
        "country": "JP"
    },
    {
        "name": "Karen Dennis",
        "age": 25,
        "country": "UK"
    },
    {
        "name": "Jennifer Ray",
        "age": 29,
        "country": "US"
    },
    {
        "name": "Miguel Williams",
        "age": 28,
        "country": "FR"
    },
    {
        "name": "Erica Gamble",
        "age": 41,
        "country": "FR"
    },
    {
        "name": "Christopher Johnson",
        "age": 55,
        "country": "JP"
    },
    {
        "name": "Lisa Conway",
        "age": 20,
        "country": "JP"
    },
    {
        "name": "Anthony Johnston",
        "age": 59,
        "country": "DE"
    },
    {
        "name": "Mary Montgomery",
        "age": 32,
        "country": "AU"
    },
    {
        "name": "Tammy Anderson",
        "age": 56,
        "country": "AU"
    },
    {
        "name": "Judy Warner",
        "age": 22,
        "country": "FR"
    },
    {
        "name": "Brenda Hopkins",
        "age": 18,
        "country": "UK"
    },
    {
        "name": "William Roman",
        "age": 25,
        "country": "CA"
    },
    {
        "name": "Debra Hernandez",
        "age": 33,
        "country": "UK"
    },
    {
        "name": "Adam Kelly",
        "age": 54,
        "country": "AU"
    },
    {
        "name": "Cindy Weber",
        "age": 56,
        "country": "AU"
    },
    {
        "name": "Terry Thomas",
        "age": 44,
        "country": "DE"
    },
    {
        "name": "Vicki Harris",
        "age": 34,
        "country": "BR"
    },
    {
        "name": "Sergio Cuevas",
        "age": 26,
        "country": "JP"
    },
    {
        "name": "Linda Moore",
        "age": 28,
        "country": "FR"
    },
    {
        "name": "Megan Chang",
        "age": 19,
        "country": "BR"
    },
    {
        "name": "Tracy Hunt",
        "age": 39,
        "country": "DE"
    },
    {
        "name": "Michael Burgess PhD",
        "age": 52,
        "country": "US"
    },
    {
        "name": "Billy White",
        "age": 50,
        "country": "JP"
    },
    {
        "name": "Lisa Simmons",
        "age": 31,
        "country": "JP"
    },
    {
        "name": "Stephanie Mays",
        "age": 29,
        "country": "JP"
    },
    {
        "name": "David Jones",
        "age": 19,
        "country": "BR"
    },
    {
        "name": "Antonio Elliott",
        "age": 34,
        "country": "AU"
    },
    {
        "name": "Mark Williams",
        "age": 22,
        "country": "FR"
    },
    {
        "name": "Stephen Williams",
        "age": 53,
        "country": "BR"
    },
    {
        "name": "Robert Tate",
        "age": 50,
        "country": "UK"
    },
    {
        "name": "Larry Bradley",
        "age": 49,
        "country": "BR"
    },
    {
        "name": "Michael Marsh",
        "age": 31,
        "country": "UK"
    },
    {
        "name": "Zachary Lopez",
        "age": 29,
        "country": "BR"
    },
    {
        "name": "Jessica Pena",
        "age": 40,
        "country": "FR"
    },
    {
        "name": "Diana Miller",
        "age": 31,
        "country": "US"
    },
    {
        "name": "Julie Weber",
        "age": 40,
        "country": "DE"
    },
    {
        "name": "William Barber",
        "age": 60,
        "country": "JP"
    },
    {
        "name": "Heidi Rogers",
        "age": 50,
        "country": "BR"
    },
    {
        "name": "James Fuller",
        "age": 57,
        "country": "BR"
    },
    {
        "name": "Christopher Moore",
        "age": 40,
        "country": "FR"
    },
    {
        "name": "Jordan Schaefer",
        "age": 31,
        "country": "JP"
    },
    {
        "name": "Tiffany Hill",
        "age": 33,
        "country": "BR"
    },
    {
        "name": "Courtney Clark",
        "age": 19,
        "country": "FR"
    },
    {
        "name": "Walter May",
        "age": 55,
        "country": "FR"
    }
]